sweet_logs/__init__.py
sweet_logs/config.py
sweet_logs/formatters.py
sweet_logs/hooks.py
sweet_logs/py.typed
sweet_logs/setup.py
sweet_logs/sweet_logs.py
sweet_logs-0.1.1.dist-info/AUTHORS.rst
sweet_logs-0.1.1.dist-info/LICENSE
sweet_logs-0.1.1.dist-info/METADATA
sweet_logs-0.1.1.dist-info/WHEEL
sweet_logs-0.1.1.dist-info/top_level.txt
sweet_logs-0.1.1.dist-info/RECORD
