Metadata-Version: 2.1
Name: sweet_logs
Version: 0.1.1
Summary: A collection of logging formatters, filters, and functions
Author-email: Jordan Woods <13803242+jorwoods@users.noreply.github.com>
License: GNU General Public License v3
Classifier: Programming Language :: Python :: 3
Classifier: Operating System :: OS Independent
Classifier: License :: OSI Approved :: GNU General Public License v3 (GPLv3)
Requires-Python: >=3.9
License-File: LICENSE
License-File: AUTHORS.rst
Requires-Dist: typing-extensions ; python_version < "3.12"
Provides-Extra: dev
Requires-Dist: pytest ; extra == 'dev'
Requires-Dist: mypy ==1.10.0 ; extra == 'dev'
Requires-Dist: pytest-mock ; extra == 'dev'
